tublub/__init__.py
tublub/main.py
tublub-0.3.0.dist-info/entry_points.txt
tublub-0.3.0.dist-info/LICENSE
tublub-0.3.0.dist-info/WHEEL
tublub-0.3.0.dist-info/METADATA
tublub-0.3.0.dist-info/RECORD
