Metadata-Version: 2.1
Name: tublub
Version: 0.3.0
Summary: Convert tabular data files with Tablib.
Home-page: https://github.com/harkabeeparolus/tublub
License: MIT
Keywords: tablib,csv,tsv,excel,xlsx
Author: Fredrik Mellström
Author-email: 11281108+harkabeeparolus@users.noreply.github.com
Requires-Python: >=3.8,<4.0
Classifier: Environment :: Console
Classifier: Intended Audience :: Information Technology
Classifier: License :: OSI Approved :: MIT License
Classifier: Operating System :: OS Independent
Classifier: Programming Language :: Python :: 3
Classifier: Programming Language :: Python :: 3.10
Classifier: Programming Language :: Python :: 3.8
Classifier: Programming Language :: Python :: 3.9
Classifier: Topic :: Text Processing
Classifier: Topic :: Utilities
Requires-Dist: tablib[ods,yaml,xls,cli,xlsx,html] (>=3.2.1,<4.0.0)
